kdmapi/__init__.py
kdmapi/bindings.py
kdmapi/mido_backend.py
kdmapi-1.0.2.dist-info/WHEEL
kdmapi-1.0.2.dist-info/METADATA
kdmapi-1.0.2.dist-info/RECORD
