Metadata-Version: 2.1
Name: kdmapi
Version: 1.0.2
Summary: KDMAPI (Keppy's Direct MIDI API) wrapper for Python
Home-page: https://github.com/python-midi/kdmapi
License: LGPL-3.0-or-later
Author: Sebastiano Barezzi
Author-email: barezzisebastiano@gmail.com
Requires-Python: >=3.8,<4.0
Classifier: License :: OSI Approved :: GNU Lesser General Public License v3 or later (LGPLv3+)
Classifier: Programming Language :: Python :: 3
Classifier: Programming Language :: Python :: 3.10
Classifier: Programming Language :: Python :: 3.8
Classifier: Programming Language :: Python :: 3.9
Project-URL: Repository, https://github.com/python-midi/kdmapi
